bigblackboxprotobuf-1.0.2.dist-info/licenses/LICENSE
blackboxprotobuf/__init__.py
blackboxprotobuf/lib/__init__.py
blackboxprotobuf/lib/interface.py
blackboxprotobuf/lib/types/__init__.py
blackboxprotobuf/lib/types/fixed.py
blackboxprotobuf/lib/types/length_delim.py
blackboxprotobuf/lib/types/type_maps.py
blackboxprotobuf/lib/types/varint.py
bigblackboxprotobuf-1.0.2.dist-info/METADATA
bigblackboxprotobuf-1.0.2.dist-info/WHEEL
bigblackboxprotobuf-1.0.2.dist-info/top_level.txt
bigblackboxprotobuf-1.0.2.dist-info/RECORD
