Metadata-Version: 2.4
Name: bigblackboxprotobuf
Version: 1.0.2
Summary: Library for reading protobuf buffers without .proto definitions
Home-page: https://github.com/15yoDungeonMaster/blackboxprotobuf
Author: Yogesh Khatri
Author-email: yogesh@swiftforensics.com
License: MIT License
Classifier: Programming Language :: Python :: 3
Classifier: License :: OSI Approved :: MIT License
Classifier: Operating System :: OS Independent
Requires-Python: >=3.6
License-File: LICENSE
Requires-Dist: protobuf>=3.20.3
Dynamic: author
Dynamic: author-email
Dynamic: classifier
Dynamic: description
Dynamic: description-content-type
Dynamic: home-page
Dynamic: license
Dynamic: license-file
Dynamic: requires-dist
Dynamic: requires-python
Dynamic: summary
